cloudmatica/__init__.py
cloudmatica-0.0.11.dist-info/LICENSE
cloudmatica-0.0.11.dist-info/METADATA
cloudmatica-0.0.11.dist-info/WHEEL
cloudmatica-0.0.11.dist-info/entry_points.txt
cloudmatica-0.0.11.dist-info/top_level.txt
cloudmatica-0.0.11.dist-info/RECORD
