Metadata-Version: 2.1
Name: cloudmatica
Version: 0.0.11
Summary: Cloudmatica suite of tools
Home-page: https://github.com/vbalasu/cloudmatica
Author: Vijay Balasubramaniam
Author-email: vbalasu@gmail.com
License: UNKNOWN
Project-URL: Bug Tracker, https://github.com/vbalasu/cloudmatica/issues
Platform: UNKNOWN
Classifier: Programming Language :: Python :: 3
Classifier: License :: OSI Approved :: MIT License
Classifier: Operating System :: OS Independent
Requires-Python: >=3.6
License-File: LICENSE
Requires-Dist: requests
